tephiplt/__init__.py
tephiplt/__main__.py
tephiplt/tephiplt.py
tephiplt-0.0.8.dist-info/LICENSE
tephiplt-0.0.8.dist-info/METADATA
tephiplt-0.0.8.dist-info/WHEEL
tephiplt-0.0.8.dist-info/top_level.txt
tephiplt-0.0.8.dist-info/RECORD
