Metadata-Version: 2.1
Name: tephiplt
Version: 0.0.8
Summary: plotting a tephigram
Home-page: https://github.com/simonom/outreach
Author: Simon O'Meara
Author-email: simon.omeara@manchester.ac.uk
License: UNKNOWN
Keywords: python,meteorology,tephigram,atmospheric physics
Platform: UNKNOWN
Classifier: Programming Language :: Python :: 3
Classifier: License :: OSI Approved :: GNU General Public License v3 (GPLv3)
Classifier: Operating System :: OS Independent
Requires-Python: >=3.0
Requires-Dist: numpy
Requires-Dist: matplotlib
Requires-Dist: ipdb
Requires-Dist: scipy
